fulladder/full_adder.v
module full_adder(a,b,cin,s,cout);
input a,b,cin;
output s,cout;
wire d;
xor x1(d,a,b);
xor x2(s,d,cin);
assign cout=(a&cin)|(a&b)|(b&cin);
endmodule

fulladder/test.v
`include "full_adder.v"
module full_adder_tb;
reg a,b,cin;
wire sum,carry;
full_adder uut(
  .a(a),.b(b),.cin(cin),.s(sum),.cout(carry)
);
initial begin
  $dumpfile("full_adder_tb.vcd");
  $dumpvars(0,full_adder_tb);
end
initial begin
 a=0,b=0,cin=0;
 #10
 a=0,b=0,cin=1;
 #10
 a=0,b=1,cin=0;
 #10
 a=0,b=1,cin=1;
 #10
 a=1,b=0,cin=0;
 #10
 a=1,b=0,cin=1;
 #10
 a=1,b=1,cin=0;
 #10
 a=1,b=1,cin=1;
end
initial begin
  $monitor("a=%d,b=%d,cin=%d,sum=%d,carry=%d",a,b,cin,sum,carry);
end
endmodule

fulladder/full_adder_tb.vcd
$date
	Sun Dec 04 11:42:07 2022
$end
$version
	Icarus Verilog
$end
$timescale
	1s
$end
$scope module full_adder_tb $end
$var wire 1 ! carry $end
$var wire 1 " sum $end
$var reg 1 # a $end
$var reg 1 $ b $end
$var reg 1 % cin $end
$scope module uut $end
$var wire 1 & a $end
$var wire 1 ' b $end
$var wire 1 ( cin $end
$var wire 1 ! cout $end
$var wire 1 ) d $end
$var wire 1 " s $end
$upscope $end
$upscope $end
$enddefinitions $end
#0
$dumpvars
0)
0(
0'
0&
0%
0$
0#
0"
0!
$end
#10
1"
1%
1(
#20
1)
0%
0(
1$
1'
#30
1!
0"
1%
1(
#40
0!
1"
0%
0(
0$
0'
1#
1&
#50
1!
0"
1%
1(
#60
0)
0%
0(
1$
1'
#70
1"
1%
1(
