fuh/full_adder.v
module full_adder(a,b,c,sum,carry);
input a,b,c;
output sum,carry;
wire x,y,z;
half_adder h1(a,b,x,y);
half_adder h2(x,c,sum,z);
or(carry,y,z);
endmodule

module half_adder(a,b,s,c);
input a,b;
output s,c;
xor (s,a,b);
and(c,a,b);
endmodule

fuh/full_adder_tb.v
`include "full_adder.v"
module full_adder_tb;
reg a,b,c;
wire sum,carry;
full_adder uut(
  .a(a),.b(b),.c(c),.sum(sum),.carry(carry)
);
initial begin
  $dumpfile("full_adder_tb.vcd");
  $dumpvars(0,full_adder_tb);
end
initial begin
 a=0;b=0;c=0;
 #10
 a=0;b=0;c=1;
 #10
 a=0;b=1;c=0;
 #10
 a=0;b=1;c=1;
 #10
 a=1;b=0;c=0;
 #10
 a=1;b=0;c=1;
 #10
 a=1;b=1;c=0;
 #10
 a=1;b=1;c=1;
end
initial begin
  $monitor("a=%d,b=%d,c=%d,carry=%d,sum=%d",a,b,c,carry,sum);
end
endmodule

fuh/full_adder_tb.vcd
$date
	Sun Dec 04 15:00:22 2022
$end
$version
	Icarus Verilog
$end
$timescale
	1s
$end
$scope module full_adder_tb $end
$var wire 1 ! carry $end
$var wire 1 " sum $end
$var reg 1 # a $end
$var reg 1 $ b $end
$var reg 1 % c $end
$scope module uut $end
$var wire 1 & a $end
$var wire 1 ' b $end
$var wire 1 ( c $end
$var wire 1 ! carry $end
$var wire 1 " sum $end
$var wire 1 ) x $end
$var wire 1 * y $end
$var wire 1 + z $end
$scope module h1 $end
$var wire 1 & a $end
$var wire 1 ' b $end
$var wire 1 * c $end
$var wire 1 ) s $end
$upscope $end
$scope module h2 $end
$var wire 1 ) a $end
$var wire 1 ( b $end
$var wire 1 + c $end
$var wire 1 " s $end
$upscope $end
$upscope $end
$upscope $end
$enddefinitions $end
#0
$dumpvars
0+
0*
0)
0(
0'
0&
0%
0$
0#
0"
0!
$end
#10
1"
1%
1(
#20
1)
0%
0(
1$
1'
#30
1!
0"
1+
1%
1(
#40
0!
1"
0+
0%
0(
0$
0'
1#
1&
#50
1!
0"
1+
1%
1(
#60
0+
0)
1*
0%
0(
1$
1'
#70
1"
1%
1(
