nor2/nor.v
module NOR(input a, b, c, output f3,f4);
wire m3, m4; 
nor U1 (m3,a,b);
nor U2 (f3,m3,c); 
nor U3 (m4,b,c);
nor U4 (f4,a,m4); 
endmodule

nor2/nortb.v
`include"nor.v"
module nortb;
reg a,b,c;
wire f3,f4;
NOR uut (.a(a),.b(b),.c(c),.f3(f3),.f4(f4));
initial begin
    $dumpfile("nortb.vcd");
    $dumpvars(0,nortb);
end
initial begin
a=0; b=0; c=0;
#200 
a=0; b=0; c=1;
#200 
a=0; b=1; c=0;
#200 
a=0; b=1; c=1;
#200 
a=1; b=0; c=0;
#200 
a=1; b=0; c=1;
#200 
a=1; b=1; c=0;
#200 
a=1; b=1; c=1;
end
initial begin
$monitor("a=%d,b=%d,c=%d,f3=%d,f4=%d",a,b,c,f3,f4);
end
endmodule

nor2/nortb.vcd
$date
	Mon Dec 05 13:23:44 2022
$end
$version
	Icarus Verilog
$end
$timescale
	1s
$end
$scope module nortb $end
$var wire 1 ! f3 $end
$var wire 1 " f4 $end
$var reg 1 # a $end
$var reg 1 $ b $end
$var reg 1 % c $end
$scope module uut $end
$var wire 1 & a $end
$var wire 1 ' b $end
$var wire 1 ( c $end
$var wire 1 ! f3 $end
$var wire 1 " f4 $end
$var wire 1 ) m3 $end
$var wire 1 * m4 $end
$upscope $end
$upscope $end
$enddefinitions $end
#0
$dumpvars
1*
1)
0(
0'
0&
0%
0$
0#
0"
0!
$end
#200
1"
0*
1%
1(
#400
1!
0)
0%
0(
1$
1'
#600
0!
1%
1(
#800
1!
1*
0"
0%
0(
0$
0'
1#
1&
#1000
0!
0*
1%
1(
#1200
1!
0%
0(
1$
1'
#1400
0!
1%
1(
