mealy/mealy_halfadder.v
module half_adder_fsm (
    input wire clk,
    input wire rst,
    input wire a,
    input wire b,
    output reg sum,
    output reg carry
);

    // State encoding
    localparam S0 = 2'b00,
               S1 = 2'b01,
               S2 = 2'b10,
               S3 = 2'b11;

    reg [1:0] current_state, next_state;

    // State register
    always @(posedge clk or posedge rst) begin
        if (rst)
            current_state <= S0;
        else
            current_state <= next_state;
    end

    // Next state logic
    always @(*) begin
        case (current_state)
            S0: next_state = {a, b};
            S1: next_state = {a, b};
            S2: next_state = {a, b};
            S3: next_state = {a, b};
            default: next_state = S0;
        endcase
    end

    // Output logic
    always @(*) begin
        case (current_state)
            S0: {carry, sum} = 2'b00;
            S1: {carry, sum} = 2'b01;
            S2: {carry, sum} = 2'b01;
            S3: {carry, sum} = 2'b10;
            default: {carry, sum} = 2'b00;
        endcase
    end

endmodule

mealy/mealy_halfadder_tb.v
`include "mealy_halfadder.v"
module half_adder_fsm_tb;

    reg clk;
    reg rst;
    reg a;
    reg b;
    wire sum;
    wire carry;

    // Instantiate the half adder FSM
    half_adder_fsm uut (
        .clk(clk),
        .rst(rst),
        .a(a),
        .b(b),
        .sum(sum),
        .carry(carry)
    );

    // Clock generation
    initial begin
        clk = 0;
        rst = 1;
        forever #5 clk = ~clk;
        forever #10 rst= ~rst;
    end

    // rst generation
        initial begin
        rst = 1;
        forever #10 rst= ~rst;
    end

    // Test stimulus
    initial begin
        // Initialize inputs
        a = 0;
        b = 0;

        // Dump waveforms
        $dumpfile("half_adder_fsm_tb.vcd");
        $dumpvars(0, half_adder_fsm_tb);

        // Test all input combinations
        #20 a = 0; b = 0;
        #20 a = 0; b = 1;
        #20 a = 1; b = 0;
        #20 a = 1; b = 1;

        // End simulation
        #20 $finish;
    end

    // Monitor outputs
    initial begin
        $monitor("Time=%0t a=%b b=%b sum=%b carry=%b", $time, a, b, sum, carry);
    end

endmodule

mealy/half_adder_fsm_tb.vcd
$date
	Wed Aug 28 17:57:09 2024
$end
$version
	Icarus Verilog
$end
$timescale
	1s
$end
$scope module half_adder_fsm_tb $end
$var wire 1 ! sum $end
$var wire 1 " carry $end
$var reg 1 # a $end
$var reg 1 $ b $end
$var reg 1 % clk $end
$var reg 1 & rst $end
$scope module uut $end
$var wire 1 # a $end
$var wire 1 $ b $end
$var wire 1 % clk $end
$var wire 1 & rst $end
$var parameter 2 ' S0 $end
$var parameter 2 ( S1 $end
$var parameter 2 ) S2 $end
$var parameter 2 * S3 $end
$var reg 1 " carry $end
$var reg 2 + current_state [1:0] $end
$var reg 2 , next_state [1:0] $end
$var reg 1 ! sum $end
$upscope $end
$upscope $end
$enddefinitions $end
$comment Show the parameter values. $end
$dumpall
b11 *
b10 )
b1 (
b0 '
$end
#0
$dumpvars
b0 ,
b0 +
1&
0%
0$
0#
0"
0!
$end
#5
1%
#10
0%
0&
#15
1%
#20
0%
1&
#25
1%
#30
0%
0&
#35
1%
#40
b1 ,
0%
1&
1$
#45
1%
#50
0%
0&
#55
1!
b1 +
1%
#60
0!
b0 +
b10 ,
0%
1&
0$
1#
#65
1%
#70
0%
0&
#75
1!
b10 +
1%
#80
0!
b0 +
b11 ,
0%
1&
1$
#85
1%
#90
0%
0&
#95
1"
b11 +
1%
#100
0"
b0 +
0%
1&
